{"name":"rthunder","description":"Rolling Thunder (new version)","system":"mame","parentSystem":"namcos86","roms":["rthunder"],"biosFiles":[],"hasSamples":false,"nativeResolution":[288,224],"players":2,"controls":{"1":{"buttons":2,"type":"joy","ways":"4"},"2":{"buttons":2,"type":"joy","ways":"4"}},"numberOfButtons":2,"buttonLabels":["Shoot","Jump"],"alternating":true,"story":"Rolling Thunder is a single-player scrolling platform shoot-em-up in which a James Bond-esque secret agent codenamed 'Albatross' has been ordered by the Rolling Thunder anti-espionage unit to stop the criminal organization known as Geldra. Albatross must also rescue captured field agent, Lelia Blitz and overthrow Geldra's leader, Maboo.","genre":"Platform","manufacturer":"Namco","year":1986,"rating":"AAMA - Yellow (Animated Violence Mild)","mature":false,"crc":""}