{"name":"zaxxon","description":"Zaxxon (set 1)","system":"mame","parentSystem":"zaxxon","roms":["zaxxon"],"biosFiles":[],"hasSamples":true,"nativeResolution":[224,256],"players":2,"controls":{"1":{"buttons":1,"type":"joy","ways":"8"},"2":{"buttons":1,"type":"joy","ways":"8"}},"numberOfButtons":1,"buttonLabels":["Fire"],"alternating":true,"story":"Zaxxon is an isometric scrolling shoot-em-up in which the player pilots an armed spaceship and must penetrate heavily-fortified enemy bases, destroying enemy ships and installations before reaching the final confrontation with a giant armoured robot.","genre":"Shoot-'Em-Up","manufacturer":"Sega","year":1982,"rating":"AAMA - Green (Suitable For All Ages)","mature":false,"crc":""}