{"name":"720","description":"720 Degrees (rev 4)","system":"mame","parentSystem":"atarisy2","roms":["720"],"biosFiles":[],"hasSamples":false,"nativeResolution":[512,384],"players":1,"controls":{"1":{"buttons":2,"type":"dial"}},"numberOfButtons":2,"buttonLabels":["Kick","Jump"],"spinner":"dial","spinnerLabels":["Rotate Right","Rotate Left"],"alternating":true,"genre":"Sports/Skateboarding","manufacturer":"Atari Games","year":1986,"rating":"AAMA - Green (Suitable For All Ages)","mature":false,"crc":""}