{"name":"burningf","description":"Burning Fight (NGM-018)","system":"mame","parentSystem":"neogeo","roms":["burningf","neogeo"],"biosFiles":["neogeo"],"hasSamples":false,"nativeResolution":[320,224],"players":2,"controls":{"1":{"buttons":4,"type":"joy","ways":"8"},"2":{"buttons":4,"type":"joy","ways":"8"}},"story":"Duke and Billy, two popular and renowned New York City Police detectives, are hot on the trail of a dangerous Japanese crime syndicate. Their investigation has led them to the mean streets of Japan (Stage 1 takes place in Osaka with famous landmarks in the Dontonbori and Ebisu Neighborhoods) where they meet a police officer and martial arts expert named Ryu. Ryu agrees to join the NYPD detectives as they track down the crime syndicate bosses and end their reign of terror once and for all.","genre":"Beat-'Em-Up","manufacturer":"SNK","year":1991,"rating":"AAMA - Yellow (Animated Violence Mild)","mature":false,"crc":""}