{"name":"edf","description":"E.D.F.: Earth Defense Force (set 1)","system":"mame","parentSystem":"megasys1","roms":["edf"],"biosFiles":[],"hasSamples":false,"nativeResolution":[256,224],"players":2,"controls":{"1":{"buttons":2,"type":"joy","ways":"8"},"2":{"buttons":2,"type":"joy","ways":"8"}},"story":"The graphics will dazzle you, the speed will astound you... but if you don't think fast and shoot faster, you won't have a chance against the alien firestorm. Because in EARTH DEFENSE FORCE, the best defense is always a great offense. So get ready to hit first and hit fast!","genre":"Shoot-'Em-Up","manufacturer":"Jaleco","year":1991,"rating":"AAMA - Green (Suitable For All Ages)","mature":false,"crc":"1d877538"}