{"name":"pbobble2","description":"Puzzle Bobble 2 (Ver 2.3O 1995/07/31)","system":"mame","parentSystem":"taito_f3","roms":["pbobble2"],"biosFiles":[],"hasSamples":false,"nativeResolution":[320,232],"players":4,"controls":{"1":{"buttons":4,"type":"dial","ways":"8"},"2":{"buttons":4,"type":"dial","ways":"8"},"3":{"buttons":4,"type":"joy","ways":"8"},"4":{"buttons":4,"type":"joy","ways":"8"}},"numberOfButtons":4,"buttonLabels":["Fire","NA","NA","NA"],"alternating":false,"genre":"Puzzle","manufacturer":"Taito Corporation Japan","year":1995,"rating":"AAMA - Green (Suitable For All Ages)","mature":false,"crc":""}